[
  {
    "record_id": "1c2b1b257f8ad1fb7aa07bdf",
    "post_id": "75c4c5d2-e041-4783-9b77-f06d22432b89",
    "text": "I don't see a position for the Sparks for a first responder to keep them from hemorrhaging great talent from that roster. I would have thought that this would have been a position of need for that franchise.",
    "source": "reddit",
    "report_title": "r/wnba: WNBA Jobs - Listings",
    "url": "https://www.reddit.com/r/wnba/comments/1rj8e9g/wnba_jobs_listings/o9rj14f/",
    "sports": [
      "WNBA"
    ],
    "date": "2026-03-11",
    "week": null,
    "season_phase": "unknown",
    "ingested_at": "2026-03-26T08:11:48.309285Z",
    "subreddit": "wnba",
    "reddit_post_id": "1rj8e9g",
    "reddit_comment_id": "o9rj14f",
    "content_type": "comment",
    "score": 10
  },
  {
    "record_id": "861156ae8a649736b4cadf38",
    "post_id": "0230dd74-d395-4159-b2c5-94504564dd1f",
    "text": "Thank you for compiling! I don't know if the league or any of the teams need a librarian/knowledge manager but that's basically my dream job!\n\nEDIT: weird comment to get downvoted!",
    "source": "reddit",
    "report_title": "r/wnba: WNBA Jobs - Listings",
    "url": "https://www.reddit.com/r/wnba/comments/1rj8e9g/wnba_jobs_listings/o8oxloo/",
    "sports": [
      "WNBA"
    ],
    "date": "2026-03-05",
    "week": null,
    "season_phase": "unknown",
    "ingested_at": "2026-03-26T08:11:48.309402Z",
    "subreddit": "wnba",
    "reddit_post_id": "1rj8e9g",
    "reddit_comment_id": "o8oxloo",
    "content_type": "comment",
    "score": 16
  },
  {
    "record_id": "2937043fdeeb87c7e425136e",
    "post_id": "ef6f5077-e9b5-4357-bef3-e1d20075be48",
    "text": "75-85k for finance manager at the storm. That is an absolute joke. A senior analyst in my city (let alone Seattle) can make 10-40k more than the high end of that range. Literally nobody should apply to that unless you\u2019re under 3 years experience. Tough job though with no experience.",
    "source": "reddit",
    "report_title": "r/wnba: WNBA Jobs - Listings",
    "url": "https://www.reddit.com/r/wnba/comments/1rj8e9g/wnba_jobs_listings/ob7kviu/",
    "sports": [
      "WNBA"
    ],
    "date": "2026-03-18",
    "week": null,
    "season_phase": "unknown",
    "ingested_at": "2026-03-26T08:11:48.309457Z",
    "subreddit": "wnba",
    "reddit_post_id": "1rj8e9g",
    "reddit_comment_id": "ob7kviu",
    "content_type": "comment",
    "score": 5
  },
  {
    "record_id": "019f445f8fed0fe4b55210a7",
    "post_id": "28be460d-ab47-4be4-bd2c-63db50ba4ad3",
    "text": "Thank you for this! Not re-signing my contract as a producer and *NEED* to find something soon, preferrably back in sports. Just applied to one of the postings!",
    "source": "reddit",
    "report_title": "r/wnba: WNBA Jobs - Listings",
    "url": "https://www.reddit.com/r/wnba/comments/1rj8e9g/wnba_jobs_listings/o8edzfc/",
    "sports": [
      "WNBA"
    ],
    "date": "2026-03-03",
    "week": null,
    "season_phase": "unknown",
    "ingested_at": "2026-03-26T08:11:48.309480Z",
    "subreddit": "wnba",
    "reddit_post_id": "1rj8e9g",
    "reddit_comment_id": "o8edzfc",
    "content_type": "comment",
    "score": 7
  },
  {
    "record_id": "41917e33084fd0c329950271",
    "post_id": "60bb53c7-2716-440a-82c6-1a7b64fa57c0",
    "text": "Interesting.  Last time i checked, I thought saw it was on April 6th. Looks like they moved it up a bit.\n\n  \nIt will be shown on ESPN \u00a0at 3:30 p.m. ET.",
    "source": "reddit",
    "report_title": "r/wnba: Expansion Draft Confirmed For April 3rd",
    "url": "https://www.reddit.com/r/wnba/comments/1s3nwed/expansion_draft_confirmed_for_april_3rd/ocgw7gl/",
    "sports": [
      "WNBA"
    ],
    "date": "2026-03-25",
    "week": null,
    "season_phase": "unknown",
    "ingested_at": "2026-03-26T08:11:48.309505Z",
    "subreddit": "wnba",
    "reddit_post_id": "1s3nwed",
    "reddit_comment_id": "ocgw7gl",
    "content_type": "comment",
    "score": 11
  },
  {
    "record_id": "c109009b957a367eefddb3f5",
    "post_id": "b1ea26cd-cbc9-45b1-b354-96e050175a11",
    "text": "With the logistics of the Expansion Draft now confirmed, which 5 players do you think your team will protect?\n\nFor Washington, my guess would be that our protections go to Sonia Citron, Kiki Iriafen, Georgia Amoore, Lucy Olsen, and Shakira Austin.\n\nThe fifth spot, which I chose Austin for, is the most difficult because it depends on whether she wants to return or not. The fact that she\u2019s a RFA would make her a very appealing pick for the expansion team, so I\u2019d rather risk losing Sheldon than almost surely lose Austin.\n\nETA: This would leave Jacy Sheldon, Nastja Claessens (draft and stash player playing for KSU), and Txell Alarcon (draft and stash) as our main candidates to lose to the expansion draft.",
    "source": "reddit",
    "report_title": "r/wnba: With the logistics of the Expansion Draft now confirmed, which 5 players do you think your team will protect?",
    "url": "https://www.reddit.com/r/wnba/comments/1s3ohlk/with_the_logistics_of_the_expansion_draft_now/",
    "sports": [
      "WNBA"
    ],
    "date": "2026-03-25",
    "week": null,
    "season_phase": "preseason",
    "ingested_at": "2026-03-26T08:11:48.309539Z",
    "subreddit": "wnba",
    "reddit_post_id": "1s3ohlk",
    "content_type": "post",
    "score": 63
  },
  {
    "record_id": "ea3daac06e37c9b16ff88345",
    "post_id": "383882b0-3771-48dd-a236-18f15fbdd1a9",
    "text": "Seattle Storm: \n\nWe have a new coach that hasn\u2019t tipped her hand at all. It\u2019s hard to predict her strategy with nothing to go on! \n\nDefinitely protecting Gabby Williams, Dominique Malonga, and Jordan Horston. I think whether they can hold onto Nneka and Skylar depends on so many variables we do not know about. I think ezi might want to go to Toronto. I would love to see Erica Wheeler on their lineup.\n\nThis leaves: \nLexie brown, Zia Cooke, Tiffany Mitchell, Britney Sykes, Mackenzie Holmes, KLS.\n\nEdited to add: also Nika. Who I suspect they will not protect &amp; probably cut",
    "source": "reddit",
    "report_title": "r/wnba: With the logistics of the Expansion Draft now confirmed, which 5 players do you think your team will protect?",
    "url": "https://www.reddit.com/r/wnba/comments/1s3ohlk/with_the_logistics_of_the_expansion_draft_now/ochbxb6/",
    "sports": [
      "WNBA"
    ],
    "date": "2026-03-25",
    "week": null,
    "season_phase": "unknown",
    "ingested_at": "2026-03-26T08:11:48.309574Z",
    "subreddit": "wnba",
    "reddit_post_id": "1s3ohlk",
    "reddit_comment_id": "ochbxb6",
    "content_type": "comment",
    "score": 17
  },
  {
    "record_id": "84a52e788fc256d350fbae8c",
    "post_id": "4c74d49f-d199-4c1a-8afb-c2187cb158fa",
    "text": "Total guess and I'm probably wrong \ud83d\ude43\n\nBut hot take, I don't think they protect Arike.\n\n\n- Paige\n- Maddy\n- Awak\n- Aziaha\n- ...and my 5th is a tossup. I could see the argument for Ty, MHA, Li or Luisa",
    "source": "reddit",
    "report_title": "r/wnba: With the logistics of the Expansion Draft now confirmed, which 5 players do you think your team will protect?",
    "url": "https://www.reddit.com/r/wnba/comments/1s3ohlk/with_the_logistics_of_the_expansion_draft_now/ocgzyf9/",
    "sports": [
      "WNBA"
    ],
    "date": "2026-03-25",
    "week": null,
    "season_phase": "unknown",
    "ingested_at": "2026-03-26T08:11:48.309618Z",
    "subreddit": "wnba",
    "reddit_post_id": "1s3ohlk",
    "reddit_comment_id": "ocgzyf9",
    "content_type": "comment",
    "score": 35
  },
  {
    "record_id": "17c8434cefbae05e7aad5ed4",
    "post_id": "8c5b8e2f-5ab0-470c-a534-6956f740d878",
    "text": "Cam, Rickea, KP, Dearica and probably Rae as Z seems about as good as gone. I think SAB would be a really good piece for an expansion team but I don\u2019t wanna see my rook go \ud83d\udc94",
    "source": "reddit",
    "report_title": "r/wnba: With the logistics of the Expansion Draft now confirmed, which 5 players do you think your team will protect?",
    "url": "https://www.reddit.com/r/wnba/comments/1s3ohlk/with_the_logistics_of_the_expansion_draft_now/ocgzugp/",
    "sports": [
      "WNBA"
    ],
    "date": "2026-03-25",
    "week": null,
    "season_phase": "unknown",
    "ingested_at": "2026-03-26T08:11:48.309643Z",
    "subreddit": "wnba",
    "reddit_post_id": "1s3ohlk",
    "reddit_comment_id": "ocgzugp",
    "content_type": "comment",
    "score": 27
  },
  {
    "record_id": "d3eda5ce4c15c4d246e604ea",
    "post_id": "5d320848-5177-4307-a189-f56c5e5422fa",
    "text": "I want them to play in a bigger arena but man I hate State Farm \ud83d\ude2d can usually recoup the entire cost of my season tickets by reselling one Fever game though so there\u2019s that.",
    "source": "reddit",
    "report_title": "r/wnba: Atlanta Dream Playing 5 Games At State Farm Arena",
    "url": "https://www.reddit.com/r/wnba/comments/1s3cyzc/atlanta_dream_playing_5_games_at_state_farm_arena/oceivks/",
    "sports": [
      "WNBA"
    ],
    "date": "2026-03-25",
    "week": null,
    "season_phase": "unknown",
    "ingested_at": "2026-03-26T08:11:48.309664Z",
    "subreddit": "wnba",
    "reddit_post_id": "1s3cyzc",
    "reddit_comment_id": "oceivks",
    "content_type": "comment",
    "score": 47
  }
 ] 